{"authorDailyContributionsMap":{"SebasFok":[{"date":"2023-10-05","commitResults":[{"hash":"aeef6fad05b0f6d0f0c354e9db79ba3ecbdfbef9","isMergeCommit":false,"messageTitle":"Update README.md","messageBody":"","fileTypesAndContributionMap":{"docs":{"insertions":1,"deletions":1}}}]},{"date":"2023-10-06","commitResults":[{"hash":"2039386c7d8e661b4e7bf66f1d4fa3ea80da23ac","isMergeCommit":false,"messageTitle":"Add AboutUs information for Sebastian","messageBody":"","fileTypesAndContributionMap":{"docs":{"insertions":13,"deletions":7}}}]},{"date":"2023-10-07","commitResults":[{"hash":"de8365c98e9274e9c7b40228f5c687bbb7774a2e","isMergeCommit":true,"messageTitle":"Merge branch \u0027master\u0027 into master","messageBody":"","fileTypesAndContributionMap":{}}]},{"date":"2023-10-08","commitResults":[{"hash":"a728f005673371e58b95131d45ece32ea30c5cf6","isMergeCommit":true,"messageTitle":"Merge pull request #4 from janelleenqi/branch-Edit-AboutUs-v1","messageBody":"janelleenqi-AboutUs","fileTypesAndContributionMap":{}},{"hash":"a53713ffad1e3c43fb6821740bbbae2f0b934975","isMergeCommit":true,"messageTitle":"Merge branch \u0027master\u0027 into master","messageBody":"","fileTypesAndContributionMap":{}},{"hash":"5677d80546a6e55ae3fc9b3c2f9efc6cc36ddfbc","isMergeCommit":true,"messageTitle":"Merge pull request #5 from ryanlohyr/master","messageBody":"Ryanlohyr-AboutUs","fileTypesAndContributionMap":{}}]}],"ryanlohyr":[{"date":"2023-10-07","commitResults":[{"hash":"a04733a9b91f0436d9e7599a9dbe7438aa6089a5","isMergeCommit":false,"messageTitle":"Update ryan portfolio","messageBody":"","fileTypesAndContributionMap":{"docs":{"insertions":2,"deletions":2}}}]}],"janelleenqi":[{"date":"2023-10-07","commitResults":[{"hash":"b8e95e351ff1f9e8058d1fa4512b9fed2a801ff5","isMergeCommit":true,"messageTitle":"Merge pull request #1 from SebasFok/SebasFok-AboutUs","messageBody":"Add AboutUs information for Sebastian","fileTypesAndContributionMap":{}},{"hash":"215bbf707ba73e12fe4a3852bd195add31b9563b","isMergeCommit":false,"messageTitle":"Edit AboutUs.md","messageBody":"","fileTypesAndContributionMap":{"docs":{"insertions":7,"deletions":7}}},{"hash":"20248cfdb579d3a65dba6b00480f73fd6818e9de","isMergeCommit":true,"messageTitle":"Merge pull request #3 from rohitcube/master","messageBody":"added profile - rohit","fileTypesAndContributionMap":{}},{"hash":"320cf1073f08efaeb681a28d2a71a2c05d03f61a","isMergeCommit":false,"messageTitle":"Edit AboutUs.md to include github","messageBody":"","fileTypesAndContributionMap":{"docs":{"insertions":7,"deletions":7}}},{"hash":"eeadb9d732a337b8cd7c73ed135d8d5aabf3ba2e","isMergeCommit":true,"messageTitle":"Merge AboutUs.md","messageBody":"","fileTypesAndContributionMap":{}}]}],"rohitcube":[{"date":"2023-10-07","commitResults":[{"hash":"a705965a345d0fb777a8268c24a02cb95f3c7009","isMergeCommit":false,"messageTitle":"added profile - rohit","messageBody":"","fileTypesAndContributionMap":{"docs":{"insertions":7,"deletions":7}}}]},{"date":"2023-10-09","commitResults":[{"hash":"67dfcdb437ce0cff8d2449ca49a32c15acb77cd7","isMergeCommit":false,"messageTitle":"Update AboutUs.md","messageBody":"","fileTypesAndContributionMap":{"docs":{"insertions":1,"deletions":1}}},{"hash":"526e6983d8cb279b409a14132ce402926860616a","isMergeCommit":true,"messageTitle":"Merge pull request #6 from rohitcube/master","messageBody":"Update AboutUs.md","fileTypesAndContributionMap":{}}]}],"CerIsaiah":[{"date":"2023-10-08","commitResults":[{"hash":"d6daf466c3aae14881d7203cec549477dda5aca9","isMergeCommit":false,"messageTitle":"Add photo and aboutUs information","messageBody":"","fileTypesAndContributionMap":{"docs":{"insertions":13,"deletions":7}}},{"hash":"621e25c4f695763044e239140052377d8211fa05","isMergeCommit":true,"messageTitle":"Add aboutUs information","messageBody":"","fileTypesAndContributionMap":{}}]},{"date":"2023-10-09","commitResults":[{"hash":"1e56807ba29080daddc8d8d177aa0110c772c699","isMergeCommit":false,"messageTitle":"Fixed merge conflicts with about us","messageBody":"","fileTypesAndContributionMap":{"docs":{"insertions":5,"deletions":5}}}]}]},"authorFileTypeContributionMap":{"SebasFok":{"docs":7,"functional-code":0,"test-code":0},"ryanlohyr":{"docs":0,"functional-code":0,"test-code":0},"janelleenqi":{"docs":6,"functional-code":0,"test-code":0},"rohitcube":{"docs":1,"functional-code":0,"test-code":0},"CerIsaiah":{"docs":11,"functional-code":0,"test-code":0}},"authorContributionVariance":{"SebasFok":20.95062,"ryanlohyr":0.8395062,"janelleenqi":41.135803,"rohitcube":10.320988,"CerIsaiah":25.0},"authorDisplayNameMap":{"SebasFok":"CS2113-T17-4 SEBA..HUNG","ryanlohyr":"CS2113-T17-4 RYAN.. RUI","janelleenqi":"CS2113-T17-4 LIOW..ELLE","rohitcube":"CS2113-T17-4 ROHI..THAN","CerIsaiah":"CS2113-T17-4 CERV..DEAN"}}
